tech_fellows/__init__.py
tech_fellows/TechFellowPlugins/graph_tools/__init__.py
tech_fellows/TechFellowPlugins/graph_tools/graph.py
tech_fellows/TechFellowPlugins/graph_tools/node.py
tech_fellows/TechFellowTools/__init__.py
tech_fellows/TechFellowTools/data_tools/__init__.py
tech_fellows/TechFellowTools/data_tools/json_file_handler.py
tech_fellows/TechFellowTools/data_tools/text_file_handler.py
tech_fellows/TechFellowTools/math_tools/__init__.py
tech_fellows/TechFellowTools/math_tools/matrix_operations.py
tech_fellows/TechFellowTools/math_tools/statistical_operations.py
tech_fellows/TechFellowTools/string_tools/__init__.py
tech_fellows/TechFellowTools/string_tools/string_case_conversions.py
tech_fellows/TechFellowTools/string_tools/string_operations.py
tech_fellows-0.1.0.dist-info/METADATA
tech_fellows-0.1.0.dist-info/WHEEL
tech_fellows-0.1.0.dist-info/RECORD
